OCI_Inference_CustomModel/OCI_Inference_CustomModel.py
OCI_Inference_CustomModel/__init__.py
OCI_Inference_CustomModel-0.2.0.dist-info/METADATA
OCI_Inference_CustomModel-0.2.0.dist-info/WHEEL
OCI_Inference_CustomModel-0.2.0.dist-info/top_level.txt
OCI_Inference_CustomModel-0.2.0.dist-info/RECORD
